orangearrow/__init__.py
orangearrow/api.py
orangearrow/builder.py
orangearrow/response.py
orangearrow-0.9.64.dist-info/LICENSE
orangearrow-0.9.64.dist-info/METADATA
orangearrow-0.9.64.dist-info/WHEEL
orangearrow-0.9.64.dist-info/top_level.txt
orangearrow-0.9.64.dist-info/RECORD
