Metadata-Version: 2.1
Name: orangearrow
Version: 0.9.64
Summary: A Python Library for interacting with the Amazon Product Advertising API.
Home-page: https://github.com/wreddily/orangearrow
Author: Joe Wilson
Author-email: UNKNOWN
License: Apache2
Platform: UNKNOWN
Classifier: License :: OSI Approved :: Apache Software License
Classifier: Programming Language :: Python :: 3
Classifier: Programming Language :: Python :: 3.4
Classifier: Programming Language :: Python :: 3.5
Requires-Dist: requests (>=2.20.0)
Requires-Dist: xmltodict (>=0.10.2)
